Workbook

Sheet الملخص
A1: حالات اختبار منصة المدى المبارك (MMC Core)
A2: تتحدّث الأرقام تلقائيًا من عمود «الحالة» في كل ورقة.
A4: الورقة | B4: المجال | C4: عدد الحالات | D4: منها P1 | E4: ناجح | F4: فاشل | G4: محجوب | H4: لم يُختبر | I4: نسبة النجاح | J4: P1 فاشلة
A5: المبيعات | B5: المبيعات والدخول | C5: =COUNTA('المبيعات'!A2:A177) | D5: =COUNTIF('المبيعات'!G2:G177,"P1") | E5: =COUNTIF('المبيعات'!I2:I177,"ناجح") | F5: =COUNTIF('المبيعات'!I2:I177,"فاشل") | G5: =COUNTIF('المبيعات'!I2:I177,"محجوب") | H5: =COUNTIF('المبيعات'!I2:I177,"لم يُختبر") | I5: =IF(C5=0,0,E5/C5) | J5: =COUNTIFS('المبيعات'!G2:G177,"P1",'المبيعات'!I2:I177,"فاشل")
A6: المالية وCRM | B6: المالية والعملاء المحتملون | C6: =COUNTA('المالية وCRM'!A2:A160) | D6: =COUNTIF('المالية وCRM'!G2:G160,"P1") | E6: =COUNTIF('المالية وCRM'!I2:I160,"ناجح") | F6: =COUNTIF('المالية وCRM'!I2:I160,"فاشل") | G6: =COUNTIF('المالية وCRM'!I2:I160,"محجوب") | H6: =COUNTIF('المالية وCRM'!I2:I160,"لم يُختبر") | I6: =IF(C6=0,0,E6/C6) | J6: =COUNTIFS('المالية وCRM'!G2:G160,"P1",'المالية وCRM'!I2:I160,"فاشل")
A7: المشاريع والخدمة | B7: المشاريع والخدمة | C7: =COUNTA('المشاريع والخدمة'!A2:A164) | D7: =COUNTIF('المشاريع والخدمة'!G2:G164,"P1") | E7: =COUNTIF('المشاريع والخدمة'!I2:I164,"ناجح") | F7: =COUNTIF('المشاريع والخدمة'!I2:I164,"فاشل") | G7: =COUNTIF('المشاريع والخدمة'!I2:I164,"محجوب") | H7: =COUNTIF('المشاريع والخدمة'!I2:I164,"لم يُختبر") | I7: =IF(C7=0,0,E7/C7) | J7: =COUNTIFS('المشاريع والخدمة'!G2:G164,"P1",'المشاريع والخدمة'!I2:I164,"فاشل")
A8: المخزون والموارد البشرية | B8: المشتريات والمخزون والموارد البشرية والإعدادات | C8: =COUNTA('المخزون والموارد البشرية'!A2:A174) | D8: =COUNTIF('المخزون والموارد البشرية'!G2:G174,"P1") | E8: =COUNTIF('المخزون والموارد البشرية'!I2:I174,"ناجح") | F8: =COUNTIF('المخزون والموارد البشرية'!I2:I174,"فاشل") | G8: =COUNTIF('المخزون والموارد البشرية'!I2:I174,"محجوب") | H8: =COUNTIF('المخزون والموارد البشرية'!I2:I174,"لم يُختبر") | I8: =IF(C8=0,0,E8/C8) | J8: =COUNTIFS('المخزون والموارد البشرية'!G2:G174,"P1",'المخزون والموارد البشرية'!I2:I174,"فاشل")
A9: الحسابات | B9: دفتر الأستاذ والقيود والترحيل التلقائي والضريبة والإقفال والفوترة الإلكترونية | C9: =COUNTA('الحسابات'!A2:A98) | D9: =COUNTIF('الحسابات'!G2:G98,"P1") | E9: =COUNTIF('الحسابات'!I2:I98,"ناجح") | F9: =COUNTIF('الحسابات'!I2:I98,"فاشل") | G9: =COUNTIF('الحسابات'!I2:I98,"محجوب") | H9: =COUNTIF('الحسابات'!I2:I98,"لم يُختبر") | I9: =IF(C9=0,0,E9/C9) | J9: =COUNTIFS('الحسابات'!G2:G98,"P1",'الحسابات'!I2:I98,"فاشل")
A10: الإجمالي | C10: =SUM(C5:C9) | D10: =SUM(D5:D9) | E10: =SUM(E5:E9) | F10: =SUM(F5:F9) | G10: =SUM(G5:G9) | H10: =SUM(H5:H9) | I10: =IF(C10=0,0,E10/C10) | J10: =SUM(J5:J9)
A12: قاعدة الإطلاق: لا تشغيل فعلي قبل أن تكون كل حالات P1 «ناجح» (عمود «P1 فاشلة» = 0 ولا P1 «لم يُختبر»).

Sheet طريقة الاستخدام
A1: طريقة الاستخدام
A2: 1. كل ورقة تغطي مجالًا من المنصة، وكل صف حالة اختبار برقم ثابت (مثل TC-D-014) — استخدم الرقم عند الإبلاغ عن مشكلة.
A3: 2. نفّذ الخطوات بالدور المذكور في «الشروط المسبقة»، ثم قارن بالنتيجة المتوقعة.
A4: 3. اختر الحالة من القائمة في عمود «الحالة»: ناجح / فاشل / محجوب (لا يمكن تنفيذها الآن) / لم يُختبر. يتلوّن الصف تلقائيًا.
A5: 4. اكتب اسمك وتاريخ الاختبار، وفي «ملاحظات» صف ما حدث فعلًا أو رقم البلاغ.
A6: 5. استخدم عامل التصفية في الصف الأول لعرض وحدة أو أولوية أو حالة معيّنة.
A8: الأولويات
A9: P1 — ضروري قبل التشغيل الفعلي (أموال، صلاحيات، أمان، ترقيم، سلامة البيانات).
A10: P2 — مهم للعمل اليومي.
A11: P3 — تحسينات وحالات نادرة.
A13: ملاحظات
A14: • بيئة الاختبار الحالية تعمل بوضع المحاكاة: واتساب والبريد والدفع والتوقيع الإلكتروني والنظام المحاسبي (FakeBackOffice) غير حقيقية — الحالات التي تحتاجها تُختبر على شكل المحاكاة أو تُعلَّم «محجوب».
A15: • مثال صف مكتمل: الحالة «فاشل»، المختبِر «أحمد»، التاريخ 2026-10-09، الملاحظات «يظهر سعر التكلفة في الرابط العام — بلاغ #12».

Sheet المبيعات
A1: الرقم | B1: الوحدة | C1: السيناريو | D1: الشروط المسبقة / الدور | E1: الخطوات | F1: النتيجة المتوقعة | G1: الأولوية | H1: النوع | I1: الحالة | J1: المختبِر | K1: تاريخ الاختبار | L1: ملاحظات / رقم البلاغ
A2: TC-A-001 | B2: الدخول والحسابات | C2: تفعيل حساب مدعو بكلمة مرور وتأكيد البريد | D2: المالك دعا بريدًا جديدًا من الإعدادات ← المستخدمون (حالة invited)؛ SMTP غير مضبوط (وضع التجربة) | E2: 1. افتح /login واضغط «فعّل حسابك» 2. أدخل البريد المدعو وكلمة مرور من 12 حرفًا 3. انسخ رابط التأكيد من سجل الخادم [auth-mail:sandbox] 4. افتح الرابط | F2: لا يُسجَّل الدخول قبل تأكيد البريد (autoSignIn=false)؛ بعد فتح الرابط يُسجَّل الدخول تلقائيًا، تتحول حالة app_user إلى active ويُربط authUserId، ويُسجَّل login_event بنتيجة success | G2: P1 | H2: وظيفي | I2: لم يُختبر
A3: TC-A-002 | B3: الدخول والحسابات | C3: رفض التسجيل لبريد غير مدعو | D3: بريد غير موجود في app_user | E3: 1. من /login اختر «فعّل حسابك» 2. أدخل بريدًا غير مدعو وكلمة مرور صالحة 3. أرسل | F3: رفض FORBIDDEN برسالة «هذا البريد غير مدعو إلى النظام — اطلب دعوة من المسؤول / This e-mail has not been invited»، ولا يُنشأ auth_user | G3: P1 | H3: أمان | I3: لم يُختبر
A4: TC-A-003 | B4: الدخول والحسابات | C4: حساب مُسجَّل دون تأكيد البريد لا يستطيع الدخول | D4: مستخدم سجّل بكلمة مرور ولم يفتح رابط التأكيد | E4: 1. حاول الدخول بالبريد وكلمة المرور | F4: يُرفض الدخول ويُطلب تأكيد البريد (requireEmailVerification)؛ لا تُنشأ جلسة | G4: P1 | H4: أمان | I4: لم يُختبر
A5: TC-A-004 | B5: الدخول والحسابات | C5: إيقاف الدخول بعد محاولات خاطئة متكررة (حد المعدل) | D5: مستخدم نشط | E5: 1. أدخل كلمة مرور خاطئة 6 مرات خلال دقيقة واحدة لنفس النقطة /api/auth/sign-in/email | F5: بعد 5 محاولات خلال 60 ثانية تُرفض المحاولة التالية بخطأ 429 (Too many requests) حتى انقضاء النافذة، ثم يعمل الدخول بكلمة المرور الصحيحة | G5: P1 | H5: أمان | I5: لم يُختبر
A6: TC-A-005 | B6: الدخول والحسابات | C6: حد محاولات رمز التحقق بخطوتين | D6: مستخدم فعّل TOTP | E6: 1. أدخل البريد وكلمة المرور الصحيحين 2. أدخل رمز TOTP خاطئًا 6 مرات خلال دقيقة | F6: بعد 5 محاولات تُرفض /two-factor/verify-totp بـ 429؛ لا تُنشأ جلسة إلا برمز صحيح | G6: P1 | H6: أمان | I6: لم يُختبر
A7: TC-A-006 | B7: الدخول والحسابات | C7: تفعيل التحقق بخطوتين من «أمان حسابي» | D7: مستخدم نشط بكلمة مرور | E7: 1. الإعدادات ← أمان حسابي ← تفعيل التحقق بخطوتين 2. امسح رمز QR بتطبيق المصادقة (المُصدر MMC Core) 3. أدخل الرمز للتأكيد 4. اخرج وادخل مجددًا | F7: يُفعَّل twoFactorEnabled؛ عند الدخول التالي يُحوَّل المستخدم لشاشة إدخال الرمز (twoFactorRedirect) ولا يدخل دونه | G7: P1 | H7: وظيفي | I7: لم يُختبر
A8: TC-A-007 | B8: الدخول والحسابات | C8: فرض MFA للأدوار المميزة (MFA_ENFORCE=true) | D8: MFA_ENFORCE=true؛ مستخدم بدور accountant دون TOTP أو مفتاح مرور | E8: 1. ادخل بكلمة المرور 2. افتح /quotes أو استدعِ GET /api/quotes 3. افتح أمان حسابي (/api/me) | F8: كل نقاط API عدا /api/me تُرجع 403 «two-factor authentication or a passkey is required for your role»؛ صفحة الأمان تعمل لتفعيل MFA، وبعد التفعيل تُفتح بقية الصفحات | G8: P1 | H8: صلاحيات | I8: لم يُختبر
A9: TC-A-008 | B9: الدخول والحسابات | C9: تسجيل الخروج ينهي الجلسة | D9: مستخدم مسجّل | E9: 1. اضغط تسجيل الخروج 2. اضغط زر الرجوع في المتصفح 3. استدعِ GET /api/quotes بالكوكي القديم | F9: لا تظهر بيانات بعد الرجوع؛ الطلب يُرجع 401 لأن الجلسة حُذفت | G9: P1 | H9: أمان | I9: لم يُختبر
A10: TC-A-009 | B10: الدخول والحسابات | C10: إيقاف مستخدم ينهي جلساته فورًا | D10: مالك + مندوب مسجّل الدخول في متصفح آخر | E10: 1. المالك: الإعدادات ← المستخدمون ← إيقاف المندوب (status=suspended) 2. المندوب: حدّث أي صفحة 3. المندوب: حاول الدخول مجددًا (بكلمة المرور أو Google) | F10: تُحذف جلسات المندوب ويُعاد إلى /login؛ الدخول التالي يُرفض «الحساب غير مفعل / Account is not active»؛ يُسجَّل audit بإجراء suspend | G10: P1 | H10: أمان | I10: لم يُختبر
A11: TC-A-010 | B11: الدخول والحسابات | C11: منع المالك من إيقاف نفسه ومن إزالة آخر مالك | D11: مالك واحد فقط في المنشأة | E11: 1. PUT /api/users/{ownId} بـ status=suspended 2. PUT /api/users/{ownId} بـ roleKeys دون owner | F11: الأول 400 «you cannot suspend yourself»؛ الثاني 400 «at least one owner must remain» | G11: P1 | H11: حالات حدّية | I11: لم يُختبر
A12: TC-A-011 | B12: الدخول والحسابات | C12: رفض بريد مدعو من نطاق غير مسموح | D12: ALLOWED_EMAIL_DOMAINS مضبوط (مثل almada.sa) ودعوة لبريد gmail.com | E12: 1. حاول التسجيل بالبريد المدعو خارج النطاق | F12: يُرفض التسجيل بنفس رسالة «غير مدعو» رغم وجود الدعوة | G12: P2 | H12: أمان | I12: لم يُختبر
A13: TC-A-012 | B13: الدخول والحسابات | C13: حد طول كلمة المرور 12–128 | D13: دعوة صالحة | E13: 1. سجّل بكلمة مرور من 11 حرفًا 2. كرر بـ 12 حرفًا 3. كرر بـ 129 حرفًا | F13: 11 و129 تُرفضان برسالة واضحة؛ 12 تُقبل | G13: P2 | H13: حالات حدّية | I13: لم يُختبر
... A177: TC-A-176 | B177: سجل التدقيق والتكامل | C177: الأداء: PDF لعرض بـ 300 بند وصور | D177: Gotenberg يعمل | E177: 1. اضغط PDF | F177: ⚠ للتأكيد (السلوك المتوقع افتراض وليس قاعدة في الكود): يصدر خلال أقل من 15 ثانية دون انقطاع، والصور مضمّنة | G177: P3 | H177: أداء | I177: لم يُختبر

Sheet المالية وCRM
A1: الرقم | B1: الوحدة | C1: السيناريو | D1: الشروط المسبقة / الدور | E1: الخطوات | F1: النتيجة المتوقعة | G1: الأولوية | H1: النوع | I1: الحالة | J1: المختبِر | K1: تاريخ الاختبار | L1: ملاحظات / رقم البلاغ
A2: TC-B-001 | B2: طلبات الدفع والدفعات | C2: جدول الدفعات الافتراضي 50/40/10 يُبنى من إجمالي العقد | D2: عقد موقّع (status=signed) بإجمالي 10,000.00 ريال مرتبط بعميل؛ مستخدم بصلاحية billing.read | E2: 1. افتح المالية ← العقد ← تبويب الفوترة (GET /finance/contracts/:id). 2. راجع الدفعات الثلاث ومبالغها. | F2: تظهر 3 دفعات بالترتيب: «دفعة مقدمة عند توقيع العقد» 5,000.00 و«دفعة قبل توريد المواد» 4,000.00 و«دفعة بعد الانتهاء من البرمجة والتسليم» 1,000.00، ومجموعها = إجمالي العقد بالضبط، و summary.remaining = 10,000.00. | G2: P1 | H2: وظيفي | I2: لم يُختبر
A3: TC-B-002 | B3: طلبات الدفع والدفعات | C3: تقريب الهللات في الجدول يجمع الإجمالي بالضبط (أكبر باقي) | D3: عقد بإجمالي 1,000.01 ريال (100001 هللة) | E3: 1. افتح تبويب الفوترة للعقد. 2. اجمع مبالغ الدفعات الثلاث يدويًا. | F3: المبالغ 500.01/400.00/100.00 أو توزيع مماثل بأكبر باقي؛ المجموع = 1,000.01 بالضبط دون فرق هللة، ولا توجد كسور أقل من الهللة. | G3: P1 | H3: حالات حدّية | I3: لم يُختبر
A4: TC-B-003 | B4: طلبات الدفع والدفعات | C4: طلب الدفعة الأولى من عقد موقّع | D4: عقد signed مرتبط بعميل له جوال؛ مستخدم بصلاحية billing.write | E4: 1. من تبويب الفوترة اضغط «طلب» على الدفعة الأولى (POST /finance/milestones/:id/request) دون dueDate. 2. افتح قائمة طلبات الدفع. | F4: يُنشأ طلب برقم MMC-PR-xxxxx بحالة draft ومبلغ 5,000.00 ورابط دفع (paymentLinkUrl) و publicToken، وتاريخ استحقاق افتراضي يقع في يوم عمل؛ تتحول الدفعة إلى requested ويُكتب سجل تدقيق request. | G4: P1 | H4: وظيفي | I4: لم يُختبر
A5: TC-B-004 | B5: طلبات الدفع والدفعات | C5: منع طلب دفعة لعقد غير موقّع | D5: عقد بحالة draft أو sent_for_signature | E5: 1. استدعِ POST /finance/milestones/:id/request لأول دفعة. | F5: 400 برسالة «the contract must be signed before requesting payments» ولا يُستهلك رقم MMC-PR. | G5: P1 | H5: تحقق من المدخلات | I5: لم يُختبر
A6: TC-B-005 | B6: طلبات الدفع والدفعات | C6: منع فتح طلبين لنفس الدفعة | D6: يوجد طلب دفع مفتوح (draft/sent/partially_paid) للدفعة الأولى | E6: 1. اطلب الدفعة نفسها مرة ثانية. | F6: 409 «payment request MMC-PR-… is already open for this milestone» ولا يُنشأ طلب ثانٍ. | G6: P1 | H6: حالات حدّية | I6: لم يُختبر
A7: TC-B-006 | B7: طلبات الدفع والدفعات | C7: إرسال طلب الدفع عبر واتساب (وضع المحاكاة) | D7: طلب بحالة draft؛ لا توجد متغيرات بيئة واتساب (sandbox) | E7: 1. اضغط «إرسال» واختر واتساب (POST /finance/payment-requests/:id/send channel=whatsapp). 2. افتح صندوق الرسائل/السجل. | F7: تتحول الحالة إلى sent ويُسجّل sentAt؛ تُسجَّل الرسالة في السجل كمحاكاة (لا تُرسل فعليًا) وتحتوي رقم الطلب والمبلغ المتبقي ورابط /p/{token}. | G7: P1 | H7: تكامل | I7: لم يُختبر
A8: TC-B-007 | B8: طلبات الدفع والدفعات | C8: إلغاء طلب دفع غير مدفوع يعيد الدفعة إلى pending | D8: طلب sent بمبلغ مدفوع 0 | E8: 1. اضغط «إلغاء» واكتب السبب (POST …/cancel reason). 2. افتح تبويب الفوترة. | F8: حالة الطلب cancelled، والدفعة تعود pending ويمكن طلبها من جديد برقم MMC-PR جديد (لا يُعاد استخدام الرقم الملغى)؛ سجل تدقيق cancel مع السبب. | G8: P1 | H8: وظيفي | I8: لم يُختبر
A9: TC-B-008 | B9: طلبات الدفع والدفعات | C9: منع إلغاء طلب مدفوع جزئيًا | D9: طلب partially_paid | E9: 1. حاول إلغاءه. | F9: 400 «a partly paid request cannot be cancelled — issue a credit note instead». | G9: P1 | H9: حالات حدّية | I9: لم يُختبر
A10: TC-B-009 | B10: طلبات الدفع والدفعات | C10: نطاق السجلات: مندوب يرى طلبات عقوده فقط | D10: مستخدم billing.read بنطاق own؛ طلبات لعقود مالكين مختلفين | E10: 1. سجّل الدخول كمندوب وافتح قائمة طلبات الدفع. 2. حاول فتح عقد زميل عبر /finance/contracts/:id. | F10: تظهر طلبات عقوده فقط؛ عقد الزميل يعيد 403/404. | G10: P1 | H10: صلاحيات | I10: لم يُختبر
A11: TC-B-010 | B11: طلبات الدفع والدفعات | C11: مستخدم بلا billing.write لا يستطيع طلب دفعة | D11: دور بصلاحية billing.read فقط | E11: 1. اضغط «طلب» أو استدعِ POST …/request. | F11: 403 ولا يظهر الزر في الواجهة. | G11: P1 | H11: صلاحيات | I11: لم يُختبر
A12: TC-B-011 | B12: طلبات الدفع والدفعات | C12: ترقيم طلبات الدفع لا يعاد استخدامه تحت التزامن | D12: عقدان موقّعان | E12: 1. اطلب دفعتين من عقدين مختلفين في اللحظة نفسها (طلبان متوازيان). | F12: رقمان MMC-PR متتاليان ومختلفان، بدون تكرار أو فجوة غير مبررة. | G12: P1 | H12: أداء | I12: لم يُختبر
A13: TC-B-012 | B13: طلبات الدفع والدفعات | C13: جدول دفعات مخصص لا يساوي 100% يُرفض | D13: مستخدم يعدّل جدول دفعات عقد مسودة | E13: 1. عدّل النسب إلى 50/30/10 (المجموع 90%). 2. احفظ. | F13: يُرفض الحفظ برسالة «payment schedule must total 100%» ولا تُنشأ دفعات. | G13: P2 | H13: تحقق من المدخلات | I13: لم يُختبر
... A160: TC-B-159 | B160: التكامل الشامل | C160: الواجهة العربية RTL في صفحات المالية و CRM والعمولات | D160: — | E160: 1. تصفح /finance/requests، /finance/invoices، /finance/vouchers، /finance/aging، /crm/pipeline، /commissions على شاشة جوال وسطح مكتب. | F160: اتجاه RTL، أرقام ومبالغ بصيغة 1,234.50 ر.س، لا تمرير أفقي، الأزرار حسب الصلاحية. | G160: P2 | H160: واجهة وعرض | I160: لم يُختبر

Sheet المشاريع والخدمة
A1: الرقم | B1: الوحدة | C1: السيناريو | D1: الشروط المسبقة / الدور | E1: الخطوات | F1: النتيجة المتوقعة | G1: الأولوية | H1: النوع | I1: الحالة | J1: المختبِر | K1: تاريخ الاختبار | L1: ملاحظات / رقم البلاغ
A2: TC-C-001 | B2: المشاريع | C2: إنشاء المشروع تلقائيًا عند توقيع العقد | D2: عقد مرسل للعميل بلا مشروع مرتبط؛ مستخدم مبيعات | E2: 1. افتح رابط التوقيع /sign/[id] بصفة العميل ووقّع العقد 2. سجّل الدخول كمدير مشاريع وافتح /projects | F2: يظهر مشروع جديد مرتبط بالعقد والعميل في المرحلة kickoff بحالة active، مع نافذة التسليم (الحد الأدنى/الأقصى من أيام العمل) من العقد، وسجل تدقيق create | G2: P1 | H2: تكامل | I2: لم يُختبر
A3: TC-C-002 | B3: المشاريع | C3: عدم تكرار المشروع عند استدعاء from-contract مرتين | D3: عقد موقّع له مشروع | E3: 1. أرسل POST /api/projects/from-contract/:contractId مرتين 2. اعرض قائمة المشاريع | F3: لا يُنشأ مشروع ثانٍ؛ يُعاد المشروع الموجود أو خطأ تعارض واضح، ولا تتكرر المهام | G3: P1 | H3: حالات حدّية | I3: لم يُختبر
A4: TC-C-003 | B4: المشاريع | C4: بوابة kickoff تمنع التقدم دون الدفعة المقدمة والاعتمادات | D4: مشروع kickoff؛ لم تُدفع المقدمة؛ لا اعتمادات | E4: 1. اضغط «التقدم للمرحلة التالية» (POST /projects/:id/advance) دون override | F4: رفض 400 «the stage gate is not met» مع قائمة الشروط الفاشلة: advance و approval:specs/door_directions/room_numbers/design | G4: P1 | H4: وظيفي | I4: لم يُختبر
A5: TC-C-004 | B5: المشاريع | C5: التقدم من kickoff بعد استيفاء كل الشروط | D5: دفعة 50% مسددة بالكامل واعتماد الأنواع الأربعة | E5: 1. اضغط التقدم | F5: ينتقل المشروع إلى procurement، يُسجَّل projectStageLog وتدقيق stage_advance دون overriddenChecks، ويبدأ عداد التسليم بتاريخ clockStartedOn | G5: P1 | H5: وظيفي | I5: لم يُختبر
A6: TC-C-005 | B6: المشاريع | C6: تجاوز البوابة مع سبب وصلاحية project.override | D6: مستخدم لديه project.override؛ بوابة procurement غير مستوفاة (لم تُدفع 40%) | E6: 1. اضغط التقدم مع تفعيل «تجاوز» وكتابة سبب 2. افتح سجل المراحل والتدقيق | F6: ينتقل للمرحلة delivery؛ يُحفظ overriddenChecks=[delivery_payment] والسبب في projectStageLog وتدقيق stage_override | G6: P1 | H6: وظيفي | I6: لم يُختبر
A7: TC-C-006 | B7: المشاريع | C7: رفض التجاوز بدون سبب | D7: مستخدم لديه project.override؛ بوابة غير مستوفاة | E7: 1. أرسل advance مع override=true وreason فارغ أو مسافات | F7: رفض 400 «a reason is required to override a stage gate» ولا تتغير المرحلة | G7: P1 | H7: تحقق من المدخلات | I7: لم يُختبر
A8: TC-C-007 | B8: المشاريع | C8: رفض التجاوز لمستخدم بلا project.override | D8: مستخدم لديه project.write فقط | E8: 1. أرسل advance مع override=true وسبب | F8: رفض 403 «overriding a stage gate requires project.override» | G8: P1 | H8: صلاحيات | I8: لم يُختبر
A9: TC-C-008 | B9: المشاريع | C9: بوابة installation تتطلب تسجيل جهاز واحد على الأقل | D9: مشروع installation بلا أجهزة | E9: 1. اضغط التقدم 2. سجّل جهازًا على المشروع ثم أعد المحاولة | F9: الأولى مرفوضة بشرط assets؛ الثانية تنتقل إلى commissioning | G9: P1 | H9: وظيفي | I9: لم يُختبر
A10: TC-C-009 | B10: المشاريع | C10: بوابة commissioning: اختبارات كل الأجهزة وطلب الدفعة 10% | D10: مشروع commissioning به 5 أجهزة؛ 4 مختبرة بنجاح؛ لم يصدر طلب الدفعة الأخيرة | E10: 1. اضغط التقدم 2. سجّل اختبارًا ناجحًا للجهاز الخامس وأصدر طلب الدفعة الأخيرة 388 3. أعد المحاولة | F10: الأولى تفشل بشرطي tests وfinal_invoice؛ الثانية تنتقل إلى handover وتُضبط deliveredOn=اليوم ويتوقف العداد | G10: P1 | H10: تكامل | I10: لم يُختبر
A11: TC-C-010 | B11: المشاريع | C11: بوابة handover: إغلاق الملاحظات وتوقيع محضر الاستلام | D11: مشروع handover بملاحظة مفتوحة واحدة | E11: 1. اضغط التقدم 2. تحقّق من الملاحظة وسجّل القبول 3. أعد المحاولة | F11: الأولى ترفض (snags, acceptance)؛ الثانية تنتقل إلى warranty | G11: P1 | H11: وظيفي | I11: لم يُختبر
A12: TC-C-011 | B12: المشاريع | C12: عداد التسليم بأيام العمل يتخطى الجمعة والسبت والعطل | D12: تقويم الشركة الافتراضي (الأحد–الخميس) وعطلة 2026-09-23؛ عداد يبدأ 2026-09-17 بنافذة 45–60 يومًا | E12: 1. افتح لوحة المشروع واقرأ targetMin/targetMax وelapsed | F12: elapsed يحسب أيام العمل بعد تاريخ البدء حتى اليوم فقط، مستبعدًا عطلة نهاية الأسبوع و23 سبتمبر؛ التواريخ المستهدفة على أيام عمل | G12: P1 | H12: حالات حدّية | I12: لم يُختبر
A13: TC-C-012 | B13: المشاريع | C13: بدء العداد = الأحدث بين المقدمة وآخر اعتماد | D13: مقدمة 2026-08-01؛ آخر اعتماد (التصميم) 2026-08-10 | E13: 1. اعرض clockStartedOn بعد اجتياز kickoff | F13: تاريخ البدء 2026-08-10 وليس تاريخ المقدمة | G13: P1 | H13: حالات حدّية | I13: لم يُختبر
... A164: TC-C-163 | B164: الذكاء الاصطناعي (وضع sandbox) | C164: حجب البيانات الحساسة قبل الإرسال | D164: نص يحتوي رقم هوية/جوال | E164: 1. استدعِ صياغة الرد وافحص سجل ai_call | F164: تظهر القيم محجوبة في المدخلات المسجلة | G164: P2 | H164: أمان | I164: لم يُختبر

Sheet المخزون والموارد البشرية
A1: الرقم | B1: الوحدة | C1: السيناريو | D1: الشروط المسبقة / الدور | E1: الخطوات | F1: النتيجة المتوقعة | G1: الأولوية | H1: النوع | I1: الحالة | J1: المختبِر | K1: تاريخ الاختبار | L1: ملاحظات / رقم البلاغ
A2: TC-D-001 | B2: الموارد البشرية — العروض الوظيفية | C2: إنشاء عرض وظيفي كمسودة بالقيم الافتراضية | D2: مستخدم بدور hr (hr.write) | E2: 1. افتح /hr/offers واضغط عرض جديد 2. أدخل اسم المرشح بالعربية والمسمى الوظيفي والراتب الأساسي 8000 وسكن 2000 ونقل 800 3. احفظ | F2: يُحفظ العرض بحالة draft برقم جديد، والقيم الافتراضية: عقد unlimited، دوام full_time، تجربة 90 يومًا، 48 ساعة، 21 يوم إجازة، إشعار 60 يومًا، صلاحية 7 أيام. الإجمالي الشهري 10,800 والسنوي 129,600 | G2: P1 | H2: وظيفي | I2: لم يُختبر
A3: TC-D-002 | B3: الموارد البشرية — العروض الوظيفية | C3: فترة التجربة 91 يومًا تعطي تحذيرًا لا خطأ | D3: عرض مسودة | E3: 1. عدّل probationDays إلى 91 2. احفظ ثم افتح العرض | F3: يظهر تحذير probation_ext (المادة 53: يتطلب اتفاقًا مكتوبًا)، ويمكن إصدار العرض | G3: P1 | H3: حالات حدّية | I3: لم يُختبر
A4: TC-D-003 | B4: الموارد البشرية — العروض الوظيفية | C4: فترة التجربة 180 مسموحة و181 تمنع الإصدار | D4: عرض مسودة ومُصدِر آخر بصلاحية hr.approve | E4: 1. اجعل التجربة 180 وأصدر العرض (يجب أن ينجح مع تحذير) 2. في عرض آخر اجعلها 181 وحاول الإصدار | F4: 180: يُصدر مع تحذير. 181: رفض 400 «Probation cannot exceed 180 days (Art. 53)» ويبقى العرض مسودة | G4: P1 | H4: حالات حدّية | I4: لم يُختبر
A5: TC-D-004 | B5: الموارد البشرية — العروض الوظيفية | C5: ساعات العمل 48 مسموحة و49 خطأ | D5: عرض مسودة | E5: 1. اجعل weeklyHours = 48 وتحقق من عدم وجود مشكلة 2. اجعلها 49 وحاول الإصدار | F5: 49 ساعة تظهر كخطأ hours (المادة 98) وتمنع الإصدار | G5: P1 | H5: حالات حدّية | I5: لم يُختبر
A6: TC-D-005 | B6: الموارد البشرية — العروض الوظيفية | C6: الإجازة السنوية أقل من 21 يومًا تمنع الإصدار | D6: عرض مسودة | E6: 1. اجعل annualLeaveDays = 20 2. حاول الإصدار من مستخدم hr.approve آخر | F6: رفض 400 «Annual leave must be at least 21 days (Art. 109)»؛ وبقيمة 21 يُقبل | G6: P1 | H6: حالات حدّية | I6: لم يُختبر
A7: TC-D-006 | B7: الموارد البشرية — العروض الوظيفية | C7: عقد محدد المدة بلا مدة بالأشهر | D7: عرض مسودة | E7: 1. اختر contractType = fixed واترك durationMonths فارغًا 2. حاول الإصدار | F7: خطأ duration «حدد مدة العقد محدد المدة بالأشهر» ويمنع الإصدار | G7: P1 | H7: تحقق من المدخلات | I7: لم يُختبر
A8: TC-D-007 | B8: الموارد البشرية — العروض الوظيفية | C8: إصدار العرض من شخص ثانٍ | D8: مسودة أنشأها مستخدم A؛ مستخدم B لديه hr.approve | E8: 1. سجّل كـ B وافتح العرض 2. اضغط إصدار | F8: تتحول الحالة إلى approved ويُسجل approvedByName ووقت الإصدار، ويظهر سجل تدقيق approve | G8: P1 | H8: وظيفي | I8: لم يُختبر
A9: TC-D-008 | B9: الموارد البشرية — العروض الوظيفية | C9: منع إصدار العرض من منشئه | D9: المستخدم A لديه hr.write وhr.approve وليس owner | E9: 1. أنشئ عرضًا كـ A 2. حاول إصداره بنفسه | F9: رفض 403 «you cannot issue an offer you prepared — another approver must issue it» | G9: P1 | H9: صلاحيات | I9: لم يُختبر
A10: TC-D-009 | B10: الموارد البشرية — العروض الوظيفية | C10: مستخدم hr بلا hr.approve لا يرى زر الإصدار | D10: دور hr الافتراضي | E10: 1. افتح عرضًا مسودة 2. حاول POST /api/hr/offers/:id/approve | F10: الزر غير ظاهر، والطلب المباشر يرجع 403 | G10: P1 | H10: صلاحيات | I10: لم يُختبر
A11: TC-D-010 | B11: الموارد البشرية — العروض الوظيفية | C11: تعديل عرض بعد إصداره ممنوع | D11: عرض approved | E11: 1. حاول PUT /api/hr/offers/:id | F11: رفض 409 «only draft offers can be edited» | G11: P1 | H11: وظيفي | I11: لم يُختبر
A12: TC-D-011 | B12: الموارد البشرية — العروض الوظيفية | C12: تسجيل قبول المرشح | D12: عرض approved | E12: 1. اضغط تسجيل الرد → قبول مع تاريخ وملاحظة | F12: الحالة accepted مع respondedAt والملاحظة، وسجل تدقيق accept | G12: P1 | H12: وظيفي | I12: لم يُختبر
A13: TC-D-012 | B13: الموارد البشرية — العروض الوظيفية | C13: تحويل العرض المقبول إلى موظف مرة واحدة | D13: عرض accepted | E13: 1. اضغط تعيين 2. تحقق من صفحة الموظف الجديد 3. اضغط تعيين مرة ثانية أو أرسل الطلب مرتين بالتوازي | F13: يُنشأ موظف واحد برقم EMP جديد بنفس بيانات العرض والراتب، ونسبة GOSI 9.75 للسعودي و0 لغيره؛ المحاولة الثانية ترفض ولا يتكرر الموظف | G13: P1 | H13: وظيفي | I13: لم يُختبر
... A174: TC-D-173 | B174: عام ومشترك | C174: الأداة القديمة — حساب التكلفة للمسؤول فقط | D174: مستخدم غير مسؤول | E174: 1. افتح ☰ خيارات | F174: لا يظهر «حساب التكلفة»؛ يظهر لـ adminIds/adminEmails | G174: P3 | H174: صلاحيات | I174: لم يُختبر

Sheet الحسابات
A1: الرقم | B1: الوحدة | C1: السيناريو | D1: الشروط المسبقة / الدور | E1: الخطوات | F1: النتيجة المتوقعة | G1: الأولوية | H1: النوع | I1: الحالة | J1: المختبِر | K1: تاريخ الاختبار | L1: ملاحظات / رقم البلاغ
A2: TC-E-001 | B2: دليل الحسابات | C2: دليل الحسابات السعودي الجاهز يظهر عند أول فتح، ومن لا يملك صلاحية الدفتر لا يراه | D2: مستأجر جديد؛ مستخدم مبيعات بلا صلاحية ledger.read ومحاسب بصلاحية ledger.read | E2: 1. بدور المحاسب افتح /accounting/accounts 2. سجّل الدخول بدور المبيعات وحاول فتح الصفحة نفسها | F2: يظهر الدليل هرميًا (مجموعات وحسابات: 1101 الصندوق، 1110 العملاء، 2110 ضريبة المخرجات، 4101 المبيعات…) وبأسماء عربية. المبيعات لا ترى بند «الحسابات» في القائمة ويُرفض الطلب 403 | G2: P1 | H2: صلاحيات | I2: لم يُختبر
A3: TC-E-002 | B3: دليل الحسابات | C3: إضافة حساب تحت مجموعة من النوع نفسه برمز فريد | D3: محاسب (ledger.write) | E3: 1. اضغط «حساب جديد» 2. اختر مجموعة المصروفات 62 وأدخل رمزًا جديدًا واسمًا عربيًا 3. احفظ | F3: يُنشأ الحساب تحت المجموعة بنوع المجموعة نفسه ويظهر في الدليل وفي قوائم اختيار القيود | G3: P2 | H3: وظيفي | I3: لم يُختبر
A4: TC-E-003 | B4: دليل الحسابات | C4: رمز حساب مكرر أو نوع لا يطابق المجموعة يُرفض | D4: محاسب | E4: 1. أنشئ حسابًا برمز موجود مسبقًا 2. أنشئ حساب إيراد تحت مجموعة مصروفات | F4: رفض 400 برسالة واضحة في الحالتين ولا يُحفظ شيء | G4: P2 | H4: تحقق من المدخلات | I4: لم يُختبر
A5: TC-E-004 | B5: دليل الحسابات | C5: لا يُغيَّر رمز الحساب أو نوعه بعد استخدامه، ويُسمح بتغيير الاسم | D5: حساب عليه حركات مرحّلة | E5: 1. افتح الحساب وعدّل الاسم العربي واحفظ 2. حاول تغيير الرمز أو النوع | F5: تغيير الاسم ينجح. تغيير الرمز/النوع مرفوض مع سبب (الحساب مستخدم) | G5: P1 | H5: حالات حدّية | I5: لم يُختبر
A6: TC-E-005 | B6: دليل الحسابات | C6: تعطيل حساب غير مستخدم وحذفه؛ الحساب المستخدم لا يُحذف | D6: حساب جديد بلا حركات وآخر عليه حركات | E6: 1. عطّل الحساب الجديد ثم احذفه 2. حاول حذف الحساب المستخدم | F6: الأول يُعطَّل ثم يُحذف ولا يظهر في الاختيار. الثاني مرفوض (يُعطَّل فقط) وتبقى حركاته | G6: P2 | H6: حالات حدّية | I6: لم يُختبر
A7: TC-E-006 | B7: دليل الحسابات | C7: تصدير الدليل إلى Excel واستيراده مع معاينة قبل التطبيق | D7: محاسب | E7: 1. اضغط «تصدير» وافتح الملف 2. أضف صفًّا لحساب جديد وعدّل اسم حساب في الملف 3. ارفعه واقرأ المعاينة ثم اضغط «تطبيق» | F7: الملف RTL بالرؤوس العربية. المعاينة تعدّد المضاف والمعدَّل والمرفوض قبل أي تغيير، والتطبيق يطبّق ما ظهر فقط | G7: P2 | H7: تكامل | I7: لم يُختبر
A8: TC-E-007 | B8: الأرصدة الافتتاحية | C8: الأرصدة الافتتاحية تحتاج صلاحية الإقفال (ledger.close) | D8: محاسب بلا ledger.close ومالك | E8: 1. بدور المحاسب افتح /accounting/opening 2. بدور المالك افتحها | F8: المحاسب لا يرى البند ويُرفض إرسال القيد 403. المالك يدخل الأرصدة | G8: P1 | H8: صلاحيات | I8: لم يُختبر
A9: TC-E-008 | B9: الأرصدة الافتتاحية | C9: تُوازَن الأرصدة تلقائيًا مقابل «الرصيد الافتتاحي لحقوق الملكية» (3301) | D9: مالك؛ تاريخ بدء التشغيل أول السنة | E9: 1. أدخل بنكًا 50,000 وصندوقًا 5,000 ورأس مال 40,000 2. احفظ | F9: يُنشأ قيد مسودة بنوع opening إجماليه 55,000، وسطر 3301 دائن 15,000 يوازن الفرق. تعطيل «موازنة تلقائية» مع فرق يُرفض 400 | G9: P1 | H9: وظيفي | I9: لم يُختبر
A10: TC-E-009 | B10: الأرصدة الافتتاحية | C10: قيد افتتاحي حيّ واحد فقط | D10: قيد افتتاحي موجود (مسودة أو مرحّل) | E10: 1. حاول إنشاء قيد افتتاحي ثانٍ | F10: رفض 409؛ يُحرَّر القائم أو يُعكس أولًا | G10: P2 | H10: حالات حدّية | I10: لم يُختبر
A11: TC-E-010 | B11: الأرصدة الافتتاحية | C11: ترحيل الافتتاحي بشخص ثانٍ يحدّد تاريخ بدء التشغيل | D11: قيد افتتاحي مسودة أعدّه المالك | E11: 1. بدور المحاسب (ledger.post) رحّل القيد 2. افتح /accounting/opening وإعدادات الحسابات | F11: يصبح posted ويظهر تاريخ البدء في الإعدادات. لا يُرحَّل شيء من المستندات المؤرخة قبله | G11: P1 | H11: وظيفي | I11: لم يُختبر
A12: TC-E-011 | B12: القيود اليدوية | C12: حفظ مسودة ناقصة مسموح لكن ترحيل قيد غير متوازن مرفوض | D12: محاسب | E12: 1. أنشئ قيدًا: مصروف 120 مدين وصندوق 100 دائن واحفظ 2. حاول ترحيله 3. صحّح الدائن إلى 120 واحفظ | F12: يُحفظ كمسودة برقم JV-NNNNNN. الترحيل مرفوض 400 (المدين لا يساوي الدائن). بعد التصحيح يُحفظ متوازنًا | G12: P1 | H12: تحقق من المدخلات | I12: لم يُختبر
A13: TC-E-012 | B13: القيود اليدوية | C13: سطور مرفوضة: مدين ودائن معًا، حساب مجموعة، أكثر من منزلتين، تاريخ قبل البدء | D13: محاسب | E13: 1. جرّب كل حالة على حدة في /accounting/journal/new | F13: كل محاولة تُرفض 400 برسالة محددة ولا يُنشأ قيد | G13: P1 | H13: تحقق من المدخلات | I13: لم يُختبر
... A98: TC-E-097 | B98: الفوترة الإلكترونية (ZATCA) | C98: مفاتيح الوحدة وشهاداتها مشفّرة في القاعدة | D98: بيئة إنتاج | E98: 1. افتح جدول einvoice_egs 2. اشغّل الـ API في الإنتاج بلا EINVOICE_KEY | F98: الأعمدة المخزّنة (private_key_enc, csid_enc…) مشفّرة AES-256-GCM لا نص صريح. بدء الإنتاج بلا المفتاح يفشل برسالة واضحة | G98: P1 | H98: أمان | I98: لم يُختبر
